{
    "Afghanistan": {
        "minkowski": [
            "Canada"
        ],
        "manhattan": [
            "Canada"
        ]
    },
    "Albania": {
        "minkowski": [
            "Canada"
        ],
        "manhattan": [
            "Canada"
        ]
    },
    "Algeria": {
        "minkowski": [
            "Canada"
        ],
        "manhattan": [
            "Canada"
        ]
    },
    "Andorra": {
        "minkowski": [
            "Canada"
        ],
        "manhattan": [
            "Canada"
        ]
    },
    "Angola": {
        "minkowski": [
            "Canada"
        ],
        "manhattan": [
            "Canada"
        ]
    },
    "Antigua and Barbuda": {
        "minkowski": [
            "Canada"
        ],
        "manhattan": [
            "China"
        ]
    },
    "Argentina": {
        "minkowski": [
            "Canada"
        ],
        "manhattan": [
            "Canada"
        ]
    },
    "Armenia": {
        "minkowski": [
            "Canada"
        ],
        "manhattan": [
            "Canada"
        ]
    },
    "Australia": {
        "minkowski": [
            "Canada"
        ],
        "manhattan": [
            "Canada"
        ]
    },
    "Austria": {
        "minkowski": [
            "Canada"
        ],
        "manhattan": [
            "Netherlands"
        ]
    },
    "Azerbaijan": {
        "minkowski": [
            "Canada"
        ],
        "manhattan": [
            "Canada"
        ]
    },
    "Bahamas": {
        "minkowski": [
            "Canada"
        ],
        "manhattan": [
            "Netherlands"
        ]
    },
    "Bahrain": {
        "minkowski": [
            "Canada"
        ],
        "manhattan": [
            "Canada"
        ]
    },
    "Bangladesh": {
        "minkowski": [
            "Canada"
        ],
        "manhattan": [
            "Canada"
        ]
    },
    "Barbados": {
        "minkowski": [
            "China"
        ],
        "manhattan": [
            "China"
        ]
    },
    "Belarus": {
        "minkowski": [
            "Canada"
        ],
        "manhattan": [
            "Canada"
        ]
    },
    "Belgium": {
        "minkowski": [
            "Canada"
        ],
        "manhattan": [
            "China"
        ]
    },
    "Belize": {
        "minkowski": [
            "Canada"
        ],
        "manhattan": [
            "Canada"
        ]
    },
    "Benin": {
        "minkowski": [
            "Canada"
        ],
        "manhattan": [
            "Canada"
        ]
    },
    "Bhutan": {
        "minkowski": [
            "Canada"
        ],
        "manhattan": [
            "Netherlands"
        ]
    },
    "Bolivia": {
        "minkowski": [
            "Canada"
        ],
        "manhattan": [
            "Canada"
        ]
    },
    "Bosnia and Herzegovina": {
        "minkowski": [
            "Canada"
        ],
        "manhattan": [
            "Canada"
        ]
    },
    "Botswana": {
        "minkowski": [
            "Canada"
        ],
        "manhattan": [
            "Canada"
        ]
    },
    "Brazil": {
        "minkowski": [
            "Canada"
        ],
        "manhattan": [
            "Canada"
        ]
    },
    "Brunei": {
        "minkowski": [
            "Canada"
        ],
        "manhattan": [
            "Canada"
        ]
    },
    "Bulgaria": {
        "minkowski": [
            "Canada"
        ],
        "manhattan": [
            "Canada"
        ]
    },
    "Burkina Faso": {
        "minkowski": [
            "Canada"
        ],
        "manhattan": [
            "Canada"
        ]
    },
    "Burma": {
        "minkowski": [
            "Canada"
        ],
        "manhattan": [
            "Canada"
        ]
    },
    "Burundi": {
        "minkowski": [
            "Canada"
        ],
        "manhattan": [
            "Canada"
        ]
    },
    "Cabo Verde": {
        "minkowski": [
            "Canada"
        ],
        "manhattan": [
            "Canada"
        ]
    },
    "Cambodia": {
        "minkowski": [
            "China"
        ],
        "manhattan": [
            "China"
        ]
    },
    "Cameroon": {
        "minkowski": [
            "Canada"
        ],
        "manhattan": [
            "Canada"
        ]
    },
    "Canada": {
        "minkowski": [
            "China"
        ],
        "manhattan": [
            "China"
        ]
    },
    "Central African Republic": {
        "minkowski": [
            "Canada"
        ],
        "manhattan": [
            "Canada"
        ]
    },
    "Chad": {
        "minkowski": [
            "Canada"
        ],
        "manhattan": [
            "Canada"
        ]
    },
    "Chile": {
        "minkowski": [
            "Canada"
        ],
        "manhattan": [
            "Canada"
        ]
    },
    "China": {
        "minkowski": [
            "Canada"
        ],
        "manhattan": [
            "Canada"
        ]
    },
    "Colombia": {
        "minkowski": [
            "Canada"
        ],
        "manhattan": [
            "Canada"
        ]
    },
    "Comoros": {
        "minkowski": [
            "Canada"
        ],
        "manhattan": [
            "Canada"
        ]
    },
    "Congo (Brazzaville)": {
        "minkowski": [
            "Canada"
        ],
        "manhattan": [
            "Canada"
        ]
    },
    "Congo (Kinshasa)": {
        "minkowski": [
            "Canada"
        ],
        "manhattan": [
            "Canada"
        ]
    },
    "Costa Rica": {
        "minkowski": [
            "Canada"
        ],
        "manhattan": [
            "Canada"
        ]
    },
    "Cote d'Ivoire": {
        "minkowski": [
            "Canada"
        ],
        "manhattan": [
            "Canada"
        ]
    },
    "Croatia": {
        "minkowski": [
            "Canada"
        ],
        "manhattan": [
            "Canada"
        ]
    },
    "Cuba": {
        "minkowski": [
            "Canada"
        ],
        "manhattan": [
            "China"
        ]
    },
    "Cyprus": {
        "minkowski": [
            "Canada"
        ],
        "manhattan": [
            "Canada"
        ]
    },
    "Czechia": {
        "minkowski": [
            "Canada"
        ],
        "manhattan": [
            "Canada"
        ]
    },
    "Denmark": {
        "minkowski": [
            "Canada"
        ],
        "manhattan": [
            "Canada"
        ]
    },
    "Diamond Princess": {
        "minkowski": [
            "Canada"
        ],
        "manhattan": [
            "Canada"
        ]
    },
    "Djibouti": {
        "minkowski": [
            "Canada"
        ],
        "manhattan": [
            "Canada"
        ]
    },
    "Dominica": {
        "minkowski": [
            "Canada"
        ],
        "manhattan": [
            "Canada"
        ]
    },
    "Dominican Republic": {
        "minkowski": [
            "Canada"
        ],
        "manhattan": [
            "Canada"
        ]
    },
    "Ecuador": {
        "minkowski": [
            "Canada"
        ],
        "manhattan": [
            "Canada"
        ]
    },
    "Egypt": {
        "minkowski": [
            "Canada"
        ],
        "manhattan": [
            "Canada"
        ]
    },
    "El Salvador": {
        "minkowski": [
            "Canada"
        ],
        "manhattan": [
            "Canada"
        ]
    },
    "Equatorial Guinea": {
        "minkowski": [
            "Canada"
        ],
        "manhattan": [
            "Canada"
        ]
    },
    "Eritrea": {
        "minkowski": [
            "Canada"
        ],
        "manhattan": [
            "Canada"
        ]
    },
    "Estonia": {
        "minkowski": [
            "Canada"
        ],
        "manhattan": [
            "China"
        ]
    },
    "Eswatini": {
        "minkowski": [
            "Canada"
        ],
        "manhattan": [
            "Canada"
        ]
    },
    "Ethiopia": {
        "minkowski": [
            "Canada"
        ],
        "manhattan": [
            "Canada"
        ]
    },
    "Fiji": {
        "minkowski": [
            "China"
        ],
        "manhattan": [
            "China"
        ]
    },
    "Finland": {
        "minkowski": [
            "Canada"
        ],
        "manhattan": [
            "Canada"
        ]
    },
    "France": {
        "minkowski": [
            "Canada"
        ],
        "manhattan": [
            "Canada"
        ]
    },
    "Gabon": {
        "minkowski": [
            "Canada"
        ],
        "manhattan": [
            "Canada"
        ]
    },
    "Gambia": {
        "minkowski": [
            "Canada"
        ],
        "manhattan": [
            "Netherlands"
        ]
    },
    "Georgia": {
        "minkowski": [
            "Canada"
        ],
        "manhattan": [
            "China"
        ]
    },
    "Germany": {
        "minkowski": [
            "Canada"
        ],
        "manhattan": [
            "Canada"
        ]
    },
    "Ghana": {
        "minkowski": [
            "Canada"
        ],
        "manhattan": [
            "Canada"
        ]
    },
    "Greece": {
        "minkowski": [
            "Canada"
        ],
        "manhattan": [
            "Canada"
        ]
    },
    "Grenada": {
        "minkowski": [
            "Canada"
        ],
        "manhattan": [
            "Canada"
        ]
    },
    "Guatemala": {
        "minkowski": [
            "Canada"
        ],
        "manhattan": [
            "Canada"
        ]
    },
    "Guinea": {
        "minkowski": [
            "Canada"
        ],
        "manhattan": [
            "Canada"
        ]
    },
    "Guinea-Bissau": {
        "minkowski": [
            "Canada"
        ],
        "manhattan": [
            "Canada"
        ]
    },
    "Guyana": {
        "minkowski": [
            "Canada"
        ],
        "manhattan": [
            "Canada"
        ]
    },
    "Haiti": {
        "minkowski": [
            "Canada"
        ],
        "manhattan": [
            "Canada"
        ]
    },
    "Holy See": {
        "minkowski": [
            "Canada"
        ],
        "manhattan": [
            "Canada"
        ]
    },
    "Honduras": {
        "minkowski": [
            "Canada"
        ],
        "manhattan": [
            "Canada"
        ]
    },
    "Hungary": {
        "minkowski": [
            "Canada"
        ],
        "manhattan": [
            "Canada"
        ]
    },
    "Iceland": {
        "minkowski": [
            "Canada"
        ],
        "manhattan": [
            "Canada"
        ]
    },
    "India": {
        "minkowski": [
            "Canada"
        ],
        "manhattan": [
            "Canada"
        ]
    },
    "Indonesia": {
        "minkowski": [
            "Canada"
        ],
        "manhattan": [
            "Canada"
        ]
    },
    "Iran": {
        "minkowski": [
            "Canada"
        ],
        "manhattan": [
            "Canada"
        ]
    },
    "Iraq": {
        "minkowski": [
            "Canada"
        ],
        "manhattan": [
            "Canada"
        ]
    },
    "Ireland": {
        "minkowski": [
            "Canada"
        ],
        "manhattan": [
            "Canada"
        ]
    },
    "Israel": {
        "minkowski": [
            "Canada"
        ],
        "manhattan": [
            "Canada"
        ]
    },
    "Italy": {
        "minkowski": [
            "Canada"
        ],
        "manhattan": [
            "Canada"
        ]
    },
    "Jamaica": {
        "minkowski": [
            "Canada"
        ],
        "manhattan": [
            "Canada"
        ]
    },
    "Japan": {
        "minkowski": [
            "Canada"
        ],
        "manhattan": [
            "Canada"
        ]
    },
    "Jordan": {
        "minkowski": [
            "Canada"
        ],
        "manhattan": [
            "Canada"
        ]
    },
    "Kazakhstan": {
        "minkowski": [
            "Canada"
        ],
        "manhattan": [
            "Canada"
        ]
    },
    "Kenya": {
        "minkowski": [
            "Canada"
        ],
        "manhattan": [
            "Canada"
        ]
    },
    "Kiribati": {
        "minkowski": [
            "China"
        ],
        "manhattan": [
            "China"
        ]
    },
    "Korea, South": {
        "minkowski": [
            "Canada"
        ],
        "manhattan": [
            "Canada"
        ]
    },
    "Kosovo": {
        "minkowski": [
            "Canada"
        ],
        "manhattan": [
            "Canada"
        ]
    },
    "Kuwait": {
        "minkowski": [
            "Canada"
        ],
        "manhattan": [
            "Canada"
        ]
    },
    "Kyrgyzstan": {
        "minkowski": [
            "Canada"
        ],
        "manhattan": [
            "Canada"
        ]
    },
    "Laos": {
        "minkowski": [
            "China"
        ],
        "manhattan": [
            "China"
        ]
    },
    "Latvia": {
        "minkowski": [
            "Canada"
        ],
        "manhattan": [
            "China"
        ]
    },
    "Lebanon": {
        "minkowski": [
            "Canada"
        ],
        "manhattan": [
            "Canada"
        ]
    },
    "Lesotho": {
        "minkowski": [
            "Canada"
        ],
        "manhattan": [
            "Canada"
        ]
    },
    "Liberia": {
        "minkowski": [
            "Canada"
        ],
        "manhattan": [
            "Canada"
        ]
    },
    "Libya": {
        "minkowski": [
            "Canada"
        ],
        "manhattan": [
            "Canada"
        ]
    },
    "Liechtenstein": {
        "minkowski": [
            "Canada"
        ],
        "manhattan": [
            "China"
        ]
    },
    "Lithuania": {
        "minkowski": [
            "Canada"
        ],
        "manhattan": [
            "China"
        ]
    },
    "Luxembourg": {
        "minkowski": [
            "Canada"
        ],
        "manhattan": [
            "Canada"
        ]
    },
    "MS Zaandam": {
        "minkowski": [
            "Canada"
        ],
        "manhattan": [
            "China"
        ]
    },
    "Madagascar": {
        "minkowski": [
            "Canada"
        ],
        "manhattan": [
            "Canada"
        ]
    },
    "Malawi": {
        "minkowski": [
            "Canada"
        ],
        "manhattan": [
            "Canada"
        ]
    },
    "Malaysia": {
        "minkowski": [
            "Canada"
        ],
        "manhattan": [
            "Canada"
        ]
    },
    "Maldives": {
        "minkowski": [
            "Canada"
        ],
        "manhattan": [
            "Canada"
        ]
    },
    "Mali": {
        "minkowski": [
            "Canada"
        ],
        "manhattan": [
            "Canada"
        ]
    },
    "Malta": {
        "minkowski": [
            "Canada"
        ],
        "manhattan": [
            "Canada"
        ]
    },
    "Marshall Islands": {
        "minkowski": [
            "Canada"
        ],
        "manhattan": [
            "China"
        ]
    },
    "Mauritania": {
        "minkowski": [
            "Canada"
        ],
        "manhattan": [
            "Canada"
        ]
    },
    "Mauritius": {
        "minkowski": [
            "Canada"
        ],
        "manhattan": [
            "Canada"
        ]
    },
    "Mexico": {
        "minkowski": [
            "Canada"
        ],
        "manhattan": [
            "Canada"
        ]
    },
    "Micronesia": {
        "minkowski": [
            "China"
        ],
        "manhattan": [
            "China"
        ]
    },
    "Moldova": {
        "minkowski": [
            "Canada"
        ],
        "manhattan": [
            "Canada"
        ]
    },
    "Monaco": {
        "minkowski": [
            "Canada"
        ],
        "manhattan": [
            "Canada"
        ]
    },
    "Mongolia": {
        "minkowski": [
            "China"
        ],
        "manhattan": [
            "China"
        ]
    },
    "Montenegro": {
        "minkowski": [
            "Canada"
        ],
        "manhattan": [
            "Canada"
        ]
    },
    "Morocco": {
        "minkowski": [
            "Canada"
        ],
        "manhattan": [
            "Canada"
        ]
    },
    "Mozambique": {
        "minkowski": [
            "Canada"
        ],
        "manhattan": [
            "Canada"
        ]
    },
    "Namibia": {
        "minkowski": [
            "Canada"
        ],
        "manhattan": [
            "Canada"
        ]
    },
    "Nepal": {
        "minkowski": [
            "Canada"
        ],
        "manhattan": [
            "Canada"
        ]
    },
    "Netherlands": {
        "minkowski": [
            "Canada"
        ],
        "manhattan": [
            "Canada"
        ]
    },
    "New Zealand": {
        "minkowski": [
            "Canada"
        ],
        "manhattan": [
            "Canada"
        ]
    },
    "Nicaragua": {
        "minkowski": [
            "Canada"
        ],
        "manhattan": [
            "Canada"
        ]
    },
    "Niger": {
        "minkowski": [
            "Canada"
        ],
        "manhattan": [
            "Canada"
        ]
    },
    "Nigeria": {
        "minkowski": [
            "Canada"
        ],
        "manhattan": [
            "Canada"
        ]
    },
    "North Macedonia": {
        "minkowski": [
            "Canada"
        ],
        "manhattan": [
            "Canada"
        ]
    },
    "Norway": {
        "minkowski": [
            "Canada"
        ],
        "manhattan": [
            "Canada"
        ]
    },
    "Oman": {
        "minkowski": [
            "Canada"
        ],
        "manhattan": [
            "Canada"
        ]
    },
    "Pakistan": {
        "minkowski": [
            "Canada"
        ],
        "manhattan": [
            "Canada"
        ]
    },
    "Panama": {
        "minkowski": [
            "Canada"
        ],
        "manhattan": [
            "Canada"
        ]
    },
    "Papua New Guinea": {
        "minkowski": [
            "China"
        ],
        "manhattan": [
            "China"
        ]
    },
    "Paraguay": {
        "minkowski": [
            "Canada"
        ],
        "manhattan": [
            "Canada"
        ]
    },
    "Peru": {
        "minkowski": [
            "Canada"
        ],
        "manhattan": [
            "Canada"
        ]
    },
    "Philippines": {
        "minkowski": [
            "Canada"
        ],
        "manhattan": [
            "Canada"
        ]
    },
    "Poland": {
        "minkowski": [
            "Canada"
        ],
        "manhattan": [
            "Canada"
        ]
    },
    "Portugal": {
        "minkowski": [
            "Canada"
        ],
        "manhattan": [
            "China"
        ]
    },
    "Qatar": {
        "minkowski": [
            "Canada"
        ],
        "manhattan": [
            "Canada"
        ]
    },
    "Romania": {
        "minkowski": [
            "Canada"
        ],
        "manhattan": [
            "Canada"
        ]
    },
    "Russia": {
        "minkowski": [
            "Canada"
        ],
        "manhattan": [
            "Canada"
        ]
    },
    "Rwanda": {
        "minkowski": [
            "Canada"
        ],
        "manhattan": [
            "Netherlands"
        ]
    },
    "Saint Kitts and Nevis": {
        "minkowski": [
            "Canada"
        ],
        "manhattan": [
            "Canada"
        ]
    },
    "Saint Lucia": {
        "minkowski": [
            "China"
        ],
        "manhattan": [
            "China"
        ]
    },
    "Saint Vincent and the Grenadines": {
        "minkowski": [
            "China"
        ],
        "manhattan": [
            "China"
        ]
    },
    "Samoa": {
        "minkowski": [
            "Canada"
        ],
        "manhattan": [
            "China"
        ]
    },
    "San Marino": {
        "minkowski": [
            "Canada"
        ],
        "manhattan": [
            "Canada"
        ]
    },
    "Sao Tome and Principe": {
        "minkowski": [
            "Canada"
        ],
        "manhattan": [
            "Canada"
        ]
    },
    "Saudi Arabia": {
        "minkowski": [
            "Canada"
        ],
        "manhattan": [
            "Canada"
        ]
    },
    "Senegal": {
        "minkowski": [
            "Canada"
        ],
        "manhattan": [
            "Canada"
        ]
    },
    "Serbia": {
        "minkowski": [
            "Canada"
        ],
        "manhattan": [
            "Canada"
        ]
    },
    "Seychelles": {
        "minkowski": [
            "China"
        ],
        "manhattan": [
            "China"
        ]
    },
    "Sierra Leone": {
        "minkowski": [
            "Canada"
        ],
        "manhattan": [
            "Canada"
        ]
    },
    "Singapore": {
        "minkowski": [
            "Canada"
        ],
        "manhattan": [
            "Canada"
        ]
    },
    "Slovakia": {
        "minkowski": [
            "Canada"
        ],
        "manhattan": [
            "Canada"
        ]
    },
    "Slovenia": {
        "minkowski": [
            "Canada"
        ],
        "manhattan": [
            "Canada"
        ]
    },
    "Solomon Islands": {
        "minkowski": [
            "Canada"
        ],
        "manhattan": [
            "China"
        ]
    },
    "Somalia": {
        "minkowski": [
            "Canada"
        ],
        "manhattan": [
            "Canada"
        ]
    },
    "South Africa": {
        "minkowski": [
            "Canada"
        ],
        "manhattan": [
            "Canada"
        ]
    },
    "South Sudan": {
        "minkowski": [
            "Canada"
        ],
        "manhattan": [
            "Canada"
        ]
    },
    "Spain": {
        "minkowski": [
            "Canada"
        ],
        "manhattan": [
            "Canada"
        ]
    },
    "Sri Lanka": {
        "minkowski": [
            "Canada"
        ],
        "manhattan": [
            "Canada"
        ]
    },
    "Sudan": {
        "minkowski": [
            "Canada"
        ],
        "manhattan": [
            "Canada"
        ]
    },
    "Suriname": {
        "minkowski": [
            "Canada"
        ],
        "manhattan": [
            "Canada"
        ]
    },
    "Sweden": {
        "minkowski": [
            "Canada"
        ],
        "manhattan": [
            "China"
        ]
    },
    "Switzerland": {
        "minkowski": [
            "Canada"
        ],
        "manhattan": [
            "Canada"
        ]
    },
    "Syria": {
        "minkowski": [
            "Canada"
        ],
        "manhattan": [
            "Canada"
        ]
    },
    "Taiwan*": {
        "minkowski": [
            "China"
        ],
        "manhattan": [
            "China"
        ]
    },
    "Tajikistan": {
        "minkowski": [
            "Canada"
        ],
        "manhattan": [
            "Canada"
        ]
    },
    "Tanzania": {
        "minkowski": [
            "Canada"
        ],
        "manhattan": [
            "Canada"
        ]
    },
    "Thailand": {
        "minkowski": [
            "China"
        ],
        "manhattan": [
            "China"
        ]
    },
    "Timor-Leste": {
        "minkowski": [
            "China"
        ],
        "manhattan": [
            "China"
        ]
    },
    "Togo": {
        "minkowski": [
            "Canada"
        ],
        "manhattan": [
            "Canada"
        ]
    },
    "Trinidad and Tobago": {
        "minkowski": [
            "Canada"
        ],
        "manhattan": [
            "Canada"
        ]
    },
    "Tunisia": {
        "minkowski": [
            "Canada"
        ],
        "manhattan": [
            "Canada"
        ]
    },
    "Turkey": {
        "minkowski": [
            "Canada"
        ],
        "manhattan": [
            "China"
        ]
    },
    "US": {
        "minkowski": [
            "Canada"
        ],
        "manhattan": [
            "Canada"
        ]
    },
    "Uganda": {
        "minkowski": [
            "Canada"
        ],
        "manhattan": [
            "Canada"
        ]
    },
    "Ukraine": {
        "minkowski": [
            "Canada"
        ],
        "manhattan": [
            "Canada"
        ]
    },
    "United Arab Emirates": {
        "minkowski": [
            "Canada"
        ],
        "manhattan": [
            "Canada"
        ]
    },
    "United Kingdom": {
        "minkowski": [
            "Canada"
        ],
        "manhattan": [
            "Canada"
        ]
    },
    "Uruguay": {
        "minkowski": [
            "China"
        ],
        "manhattan": [
            "China"
        ]
    },
    "Uzbekistan": {
        "minkowski": [
            "Canada"
        ],
        "manhattan": [
            "Canada"
        ]
    },
    "Vanuatu": {
        "minkowski": [
            "Canada"
        ],
        "manhattan": [
            "China"
        ]
    },
    "Venezuela": {
        "minkowski": [
            "Canada"
        ],
        "manhattan": [
            "Canada"
        ]
    },
    "Vietnam": {
        "minkowski": [
            "Canada"
        ],
        "manhattan": [
            "Canada"
        ]
    },
    "West Bank and Gaza": {
        "minkowski": [
            "Canada"
        ],
        "manhattan": [
            "Canada"
        ]
    },
    "Yemen": {
        "minkowski": [
            "Canada"
        ],
        "manhattan": [
            "Canada"
        ]
    },
    "Zambia": {
        "minkowski": [
            "Canada"
        ],
        "manhattan": [
            "Canada"
        ]
    },
    "Zimbabwe": {
        "minkowski": [
            "Canada"
        ],
        "manhattan": [
            "Canada"
        ]
    }
}